onnx_perf_test/__init__.py
onnx_perf_test/analyze_onnx_profile.py
onnx_perf_test/onnx_perf_test.py
onnx_perf_test/utils.py
onnx_perf_test-0.7.0.dist-info/LICENSE
onnx_perf_test-0.7.0.dist-info/METADATA
onnx_perf_test-0.7.0.dist-info/WHEEL
onnx_perf_test-0.7.0.dist-info/entry_points.txt
onnx_perf_test-0.7.0.dist-info/top_level.txt
onnx_perf_test-0.7.0.dist-info/RECORD
