Metadata-Version: 2.1
Name: onnx-perf-test
Version: 0.7.0
Summary: A simple tool to measure the performance of ONNX models in Python.
Author: Ibai Gorordo
License: MIT
Project-URL: Homepage, https://github.com/ibaiGorordo/onnx-perf-test
License-File: LICENSE
Requires-Dist: pandas
Requires-Dist: argparse
Requires-Dist: matplotlib
Requires-Dist: onnxruntime-gpu==1.18.0; sys_platform != "darwin"
Requires-Dist: onnxruntime==1.18.0; sys_platform == "darwin" and platform_machine != "arm64"
Requires-Dist: onnxruntime-silicon==1.16.3; sys_platform == "darwin" and platform_machine == "arm64"
